cloudformation/__init__.py
cloudformation/delete_stack.py
cloudformation/deploy_stack.py
cloudformation/deploy_stack_dict.py
cfn_deploy-1.0.9.dist-info/LICENSE
cfn_deploy-1.0.9.dist-info/METADATA
cfn_deploy-1.0.9.dist-info/WHEEL
cfn_deploy-1.0.9.dist-info/top_level.txt
cfn_deploy-1.0.9.dist-info/RECORD
